spotifyadbypassv2/spotifyBypassv2.py
spotifybypassv2-0.0.2.dist-info/METADATA
spotifybypassv2-0.0.2.dist-info/RECORD
spotifybypassv2-0.0.2.dist-info/WHEEL
spotifybypassv2-0.0.2.dist-info/top_level.txt
