Metadata-Version: 2.1
Name: spotifybypassv2
Version: 0.0.2
Summary: Bypasses spotify ads by closing and opening spotify
Home-page: https://github.com/Rajathbharadwaj/SpotifyAdBypass
Author: Rajath Bharadwaj
Author-email: rajathrajath940@gmail.com
License: GNU GPL v3
Platform: UNKNOWN
